coppafish/__init__.py
coppafish/__main__.py
coppafish/_version.py
coppafish/call_spots/__init__.py
coppafish/call_spots/background.py
coppafish/call_spots/background_optimised.py
coppafish/call_spots/base.py
coppafish/call_spots/bleed_matrix.py
coppafish/call_spots/dot_product.py
coppafish/call_spots/dot_product_optimised.py
coppafish/call_spots/qual_check.py
coppafish/call_spots/qual_check_optimised.py
coppafish/extract/__init__.py
coppafish/extract/base.py
coppafish/extract/deconvolution.py
coppafish/extract/fstack.py
coppafish/extract/scale.py
coppafish/find_spots/__init__.py
coppafish/find_spots/base.py
coppafish/find_spots/check_spots.py
coppafish/find_spots/detect.py
coppafish/find_spots/detect_optimised.py
coppafish/omp/__init__.py
coppafish/omp/base.py
coppafish/omp/coefs.py
coppafish/omp/coefs_optimised.py
coppafish/omp/spots.py
coppafish/pipeline/__init__.py
coppafish/pipeline/basic_info.py
coppafish/pipeline/call_reference_spots.py
coppafish/pipeline/extract_run.py
coppafish/pipeline/find_spots.py
coppafish/pipeline/get_reference_spots.py
coppafish/pipeline/omp.py
coppafish/pipeline/register.py
coppafish/pipeline/register_initial.py
coppafish/pipeline/run.py
coppafish/pipeline/stitch.py
coppafish/plot/__init__.py
coppafish/plot/raw.py
coppafish/plot/call_spots/__init__.py
coppafish/plot/call_spots/background.py
coppafish/plot/call_spots/bleed_matrix.py
coppafish/plot/call_spots/dot_product.py
coppafish/plot/call_spots/gene_counts.py
coppafish/plot/call_spots/scaled_k_means.py
coppafish/plot/call_spots/score_calc.py
coppafish/plot/call_spots/spot_colors.py
coppafish/plot/call_spots/weight.py
coppafish/plot/extract/__init__.py
coppafish/plot/extract/diagnostics.py
coppafish/plot/extract/viewer.py
coppafish/plot/find_spots/__init__.py
coppafish/plot/find_spots/n_spots.py
coppafish/plot/find_spots/viewer.py
coppafish/plot/omp/__init__.py
coppafish/plot/omp/coefs.py
coppafish/plot/omp/score_hist.py
coppafish/plot/omp/score_shape.py
coppafish-0.1.6.dist-info/LICENSE.md
coppafish-0.1.6.dist-info/METADATA
coppafish-0.1.6.dist-info/WHEEL
coppafish-0.1.6.dist-info/top_level.txt
coppafish-0.1.6.dist-info/RECORD
