Metadata-Version: 2.1
Name: coppafish
Version: 0.1.6
Summary: coppaFISH software for Python
Home-page: https://jduffield65.github.io/coppafish/
Author: Josh Duffield
Author-email: jduffield65@gmail.com
Maintainer: Reilly Tilbury
Maintainer-email: reillytilbury@gmail.com
License: MIT
Classifier: Development Status :: 4 - Beta
Classifier: Intended Audience :: Science/Research
Classifier: License :: OSI Approved :: MIT License
Classifier: Programming Language :: Python :: 3
Classifier: Topic :: Scientific/Engineering
Classifier: Topic :: Scientific/Engineering :: Bio-Informatics
Requires-Python: >=3.8
License-File: LICENSE.md
Requires-Dist: numpy
Requires-Dist: numpy-indexed
Requires-Dist: tqdm
Requires-Dist: scipy
Requires-Dist: sklearn
Requires-Dist: opencv-python-headless
Requires-Dist: scikit-image
Requires-Dist: nd2
Requires-Dist: h5py
Requires-Dist: pandas
Requires-Dist: cloudpickle
Requires-Dist: dask
Requires-Dist: joblib
Requires-Dist: threadpoolctl
Requires-Dist: cachey
Requires-Dist: sphinx
Provides-Extra: optimised
Requires-Dist: jax ; extra == 'optimised'
Requires-Dist: jaxlib ; extra == 'optimised'
Provides-Extra: plotting
Requires-Dist: matplotlib ; extra == 'plotting'
Requires-Dist: distinctipy ; extra == 'plotting'
Requires-Dist: PyQt5 ; extra == 'plotting'
Requires-Dist: magicgui ; extra == 'plotting'
Requires-Dist: ipympl ; extra == 'plotting'
Requires-Dist: napari ; extra == 'plotting'
Requires-Dist: npe2 ; extra == 'plotting'
Requires-Dist: hsluv ; extra == 'plotting'
Requires-Dist: freetype-py ; extra == 'plotting'
